gradpose/__init__.py
gradpose/gradpose.py
gradpose/util.py
gradpose-0.1.dist-info/LICENSE
gradpose-0.1.dist-info/METADATA
gradpose-0.1.dist-info/WHEEL
gradpose-0.1.dist-info/entry_points.txt
gradpose-0.1.dist-info/top_level.txt
gradpose-0.1.dist-info/RECORD
