Metadata-Version: 2.1
Name: gradpose
Version: 0.1
Summary: GradPose is a novel structural superimposition command-line tool and Python package for PDB files.
Author-email: Daniel Rademaker <dtrademaker@gmail.com>, Kevin van Geemen <kevinvg207business@gmail.com>
Project-URL: Homepage, https://github.com/X-lab-3D/fast-superimposition
Project-URL: Bug Tracker, https://github.com/X-lab-3D/fast-superimposition/issues
Classifier: Programming Language :: Python :: 3
Classifier: License :: OSI Approved :: Apache Software License
Classifier: Operating System :: OS Independent
Classifier: Topic :: Scientific/Engineering :: Bio-Informatics
Requires-Python: >=3.7
License-File: LICENSE
Requires-Dist: numpy
Requires-Dist: torch
Requires-Dist: tqdm
